addgene_mcp/__init__.py
addgene_mcp/server.py
addgene_mcp/datatypes/__init__.py
addgene_mcp/datatypes/bacterial_resistance.py
addgene_mcp/datatypes/expression.py
addgene_mcp/datatypes/has_dna_service.py
addgene_mcp/datatypes/has_viral_service.py
addgene_mcp/datatypes/is_industry.py
addgene_mcp/datatypes/pagination.py
addgene_mcp/datatypes/plasmid_type.py
addgene_mcp/datatypes/popularity.py
addgene_mcp/datatypes/query.py
addgene_mcp/datatypes/resistance_marker.py
addgene_mcp/datatypes/sequence_format.py
addgene_mcp/datatypes/services.py
addgene_mcp/datatypes/species.py
addgene_mcp/datatypes/vector_type.py
addgene_mcp/scrapy_addgene/__init__.py
addgene_mcp/scrapy_addgene/debug_output.json
addgene_mcp/scrapy_addgene/items.py
addgene_mcp/scrapy_addgene/runner.py
addgene_mcp/scrapy_addgene/scrapy.cfg
addgene_mcp/scrapy_addgene/settings.py
addgene_mcp/scrapy_addgene/test_output.json
addgene_mcp/scrapy_addgene/pipelines/__init__.py
addgene_mcp/scrapy_addgene/pipelines/duplicates.py
addgene_mcp/scrapy_addgene/pipelines/validation.py
addgene_mcp/scrapy_addgene/spiders/__init__.py
addgene_mcp/scrapy_addgene/spiders/plasmids.py
addgene_mcp/scrapy_addgene/spiders/sequences.py
addgene_mcp-0.1.3.dist-info/METADATA
addgene_mcp-0.1.3.dist-info/WHEEL
addgene_mcp-0.1.3.dist-info/entry_points.txt
addgene_mcp-0.1.3.dist-info/licenses/LICENSE
addgene_mcp-0.1.3.dist-info/RECORD
