Metadata-Version: 2.4
Name: addgene-mcp
Version: 0.1.3
Summary: MCP for Addgene - Plasmid Repository API
Author-email: antonkulaga <antonkulaga@gmail.com>
License-File: LICENSE
Requires-Python: >=3.12
Requires-Dist: eliot>=1.17.5
Requires-Dist: fastapi>=0.115.12
Requires-Dist: fastmcp>=2.8.1
Requires-Dist: httpx>=0.28.1
Requires-Dist: pycomfort>=0.0.18
Requires-Dist: pydantic>=2.8.2
Requires-Dist: pytest
Requires-Dist: pytest-asyncio
Requires-Dist: python-dotenv
Requires-Dist: requests
Requires-Dist: scrapy-splash>=0.11.1
Requires-Dist: scrapy>=2.11.2
Requires-Dist: tenacity>=8.5.0
Requires-Dist: uc-micro-py
Requires-Dist: uvicorn>=0.30.1
